{
    "test": {
        "VoqpDUFu": {
            "id": "VoqpDUFu",
            "data": "posted test data updated"
        },
        "ndG9dCYk": {
            "id": "ndG9dCYk",
            "data": "posted test data"
        }
    },
    "example": {
        "1GuUm_q7j": {
            "id": "1GuUm_q7j",
            "data": "posted test data updated",
            "aNumber": 10
        },
        "NxndJS2lA": {
            "id": "NxndJS2lA",
            "data": "test",
            "aNumber": 1
        },
        "MWA6S2P0F": {
            "id": "MWA6S2P0F",
            "data": "test",
            "aNumber": 1
        }
    }
}